LogicTT/TT.py
LogicTT/__init__.py
LogicTT-0.0.2.dist-info/LICENSE
LogicTT-0.0.2.dist-info/METADATA
LogicTT-0.0.2.dist-info/WHEEL
LogicTT-0.0.2.dist-info/top_level.txt
LogicTT-0.0.2.dist-info/RECORD
