Metadata-Version: 2.1
Name: LogicTT
Version: 0.0.2
Summary: Logic Truth Table Generator
Home-page: https://github.com/SpecialDude/LogicTT
Author: Warith Adetayo
Author-email: warithadetayo.awa@gmail.com
License: MIT
Platform: UNKNOWN
Classifier: Programming Language :: Python :: 3
Classifier: License :: OSI Approved :: MIT License
Classifier: Operating System :: OS Independent
Requires-Python: >=3
